kkappkit/.git/.DS_Store
kkappkit/.git/COMMIT_EDITMSG
kkappkit/.git/FETCH_HEAD
kkappkit/.git/HEAD
kkappkit/.git/ORIG_HEAD
kkappkit/.git/config
kkappkit/.git/description
kkappkit/.git/hooks/applypatch-msg.sample
kkappkit/.git/hooks/commit-msg.sample
kkappkit/.git/hooks/fsmonitor-watchman.sample
kkappkit/.git/hooks/post-update.sample
kkappkit/.git/hooks/pre-applypatch.sample
kkappkit/.git/hooks/pre-commit.sample
kkappkit/.git/hooks/pre-merge-commit.sample
kkappkit/.git/hooks/pre-push.sample
kkappkit/.git/hooks/pre-rebase.sample
kkappkit/.git/hooks/pre-receive.sample
kkappkit/.git/hooks/prepare-commit-msg.sample
kkappkit/.git/hooks/push-to-checkout.sample
kkappkit/.git/hooks/sendemail-validate.sample
kkappkit/.git/hooks/update.sample
kkappkit/.git/index
kkappkit/.git/info/exclude
kkappkit/.git/logs/HEAD
kkappkit/.git/logs/refs/heads/main
kkappkit/.git/logs/refs/remotes/origin/HEAD
kkappkit/.git/logs/refs/remotes/origin/main
kkappkit/.git/logs/refs/remotes/origin/master
kkappkit/.git/objects/01/8a8db3a3d68025b71c8f7cca360465df1e1568
kkappkit/.git/objects/02/799389e5f8c28c1d9dbadad3654c954d8db1db
kkappkit/.git/objects/03/17a38ee381324502c023a8497b3643d9b58934
kkappkit/.git/objects/05/13f6912a94782aeb4cb6f245fd67b2ea48f4e7
kkappkit/.git/objects/07/5c986bdca78cfa228a5a9d891822746309f7bf
kkappkit/.git/objects/09/5b7ad3977e7afdbd1eea396e3408123f9c4f4a
kkappkit/.git/objects/0b/0933362d6650d3b9c90797541faa62103a9b6d
kkappkit/.git/objects/0d/b8135d6852f92b0a95989efe27b45c76e65762
kkappkit/.git/objects/12/3484730c882b85b19a252d6eb247c960ca927f
kkappkit/.git/objects/12/56d2c71da0738b7ff96eee7e593661167d05ce
kkappkit/.git/objects/17/d9d03c89a5c1ad144ab24f3b432246d43ee4ee
kkappkit/.git/objects/19/0d1ba98f6c5fd1abaf92cad77ba22a722d8001
kkappkit/.git/objects/1a/c02a4762d47ebcbbe272d9a3b12b295c540d95
kkappkit/.git/objects/1b/4284a1f82b3c81d8a734369c4863f1e04229d4
kkappkit/.git/objects/1c/591c50284c7c35678c7a37d33af41e338b6e1e
kkappkit-0.29.0.dist-info/LICENSE
kkappkit-0.29.0.dist-info/METADATA
kkappkit-0.29.0.dist-info/WHEEL
kkappkit-0.29.0.dist-info/RECORD
