Metadata-Version: 2.1
Name: kkappkit
Version: 0.29.0
Summary: Code-generator for building small desktop applications with Python and Tkinter
Home-page: https://github.com/kakyoism/kkappkit/
License: MIT
Keywords: frontend,ui
Author: Beinan Li
Author-email: li.beinan@gmail.com
Requires-Python: >=3.11,<4.0
Classifier: License :: OSI Approved :: MIT License
Classifier: Programming Language :: Python :: 3
Classifier: Programming Language :: Python :: 3.11
Requires-Dist: GitPython
Requires-Dist: cx_freeze
Requires-Dist: kkbuild
Requires-Dist: kkpyui
Requires-Dist: kkpyutil
Project-URL: Documentation, https://github.com/kakyoism/kkappkit/README.md
Project-URL: Repository, https://github.com/kakyoism/kkappkit/
Project-URL: issues, https://github.com/kakyoism/kkappkit/issues
